nex_protocols_common_py/__init__.py
nex_protocols_common_py/authentication_protocol.py
nex_protocols_common_py/datastore_protocol.py
nex_protocols_common_py/matchmake_extension_protocol.py
nex_protocols_common_py/matchmaking_ext_protocol.py
nex_protocols_common_py/matchmaking_protocol.py
nex_protocols_common_py/matchmaking_utils.py
nex_protocols_common_py/nat_traversal_protocol.py
nex_protocols_common_py/ranking_protocol.py
nex_protocols_common_py/secure_connection_protocol.py
nex_protocols_common_py-0.2.1.dist-info/METADATA
nex_protocols_common_py-0.2.1.dist-info/WHEEL
nex_protocols_common_py-0.2.1.dist-info/top_level.txt
nex_protocols_common_py-0.2.1.dist-info/RECORD
