Metadata-Version: 2.4
Name: nex_protocols_common_py
Version: 0.2.1
Summary: NEX protocols common for use to easily create NEX Servers.
Requires-Python: >=3.7
Requires-Dist: pymongo
Requires-Dist: nintendoclients
Dynamic: requires-dist
Dynamic: requires-python
Dynamic: summary
